Metadata-Version: 1.1
Name: gmem
Version: 0.20190316.1139
Summary: Completely General Mixed Effects Models
Home-page: https://github.com/arose13/GMEM
Author: Stephen Rose
Author-email: me@stephenro.se
License: BSD
Download-URL: https://github.com/arose13/GMEM/tarball/0.20190316.1139
Platform: UNKNOWN
Classifier: Development Status :: 3 - Alpha
Classifier: Intended Audience :: Developers
Classifier: Programming Language :: Python :: 3
Classifier: Topic :: Scientific/Engineering :: Artificial Intelligence
